README
setup.py
execcontrol/__init__.py
execcontrol/controlled.py
execcontrol/parse_gdb_mi.py
pyexeccontrol.egg-info/PKG-INFO
pyexeccontrol.egg-info/SOURCES.txt
pyexeccontrol.egg-info/dependency_links.txt
pyexeccontrol.egg-info/requires.txt
pyexeccontrol.egg-info/top_level.txt