Metadata-Version: 1.0
Name: pyexeccontrol
Version: 0.0.2
Summary: An interface to gdb to control program execution
Home-page: http://packages.python.org/pyexeccontrol
Author: Francesco Bruschi
Author-email: fbrusch@gmail.com
License: BSD
Keywords: gdb debug execution
Platform: UNKNOWN
Classifier: Development Status :: 2 - Pre-Alpha
